setup.py
lds_scriptures/__init__.py
lds_scriptures/lds_scriptures.py
lds_scriptures.egg-info/PKG-INFO
lds_scriptures.egg-info/SOURCES.txt
lds_scriptures.egg-info/dependency_links.txt
lds_scriptures.egg-info/top_level.txt