Metadata-Version: 1.1
Name: lds-scriptures
Version: 0.1.2
Summary: LDS Scripture Data
Home-page: https://github.com/magland/lds_scriptures
Author: Jeremy Magland
Author-email: jeremy.magland@gmail.com
License: UNKNOWN
Platform: UNKNOWN
Classifier: Programming Language :: Python :: 3
Classifier: License :: OSI Approved :: Apache Software License
Classifier: Operating System :: OS Independent
